{
  "id": 3036,
  "problem_id": 11,
  "submitted_at": "2022-09-02T20:52:21.078278Z",
  "status": "SUCCEEDED",
  "cost": 96032866,
  "error": "",
  "file_url": "https://minivinci-submissions.s3.amazonaws.com/user247_problem_11_ff974197-222f-44b2-98e6-98f2518160fa.isl?X-Amz-Algorithm=AWS4-HMAC-SHA256&X-Amz-Credential=AKIA35VZNBCZRCI77IEN%2F20220905%2Fus-east-1%2Fs3%2Faws4_request&X-Amz-Date=20220905T072052Z&X-Amz-Expires=900&X-Amz-SignedHeaders=host&X-Amz-Signature=78fa06559fc45a814c5f23750b3aae37d548ae05cc2fafb9750a66127dad823c"
}
