{
  "id": 37868,
  "problem_id": 19,
  "submitted_at": "2022-09-04T16:45:13.942468Z",
  "status": "SUCCEEDED",
  "cost": 55484,
  "error": "",
  "file_url": "https://minivinci-submissions.s3.amazonaws.com/user247_problem_19_649776bc-341e-49f5-bd82-70b8546186d0.isl?X-Amz-Algorithm=AWS4-HMAC-SHA256&X-Amz-Credential=AKIA35VZNBCZRCI77IEN%2F20220905%2Fus-east-1%2Fs3%2Faws4_request&X-Amz-Date=20220905T071942Z&X-Amz-Expires=900&X-Amz-SignedHeaders=host&X-Amz-Signature=d3f9c114a4f36836146f651859cd599d8523942a8cc93cee20a2370f0e323e39"
}
